genomehouse/__init__.py
genomehouse/genomic_parsers.py
genomehouse/ml_models.py
genomehouse/sequence_tools.py
genomehouse/stats.py
genomehouse/utils.py
genomehouse/visualization.py
genomehouse-1.2.0.dist-info/licenses/LICENSE
tests/__init__.py
tests/test_genomic_parsers.py
tests/test_ml_models.py
tests/test_sequence_tools.py
tests/test_stats.py
tests/test_visualization.py
genomehouse-1.2.0.dist-info/METADATA
genomehouse-1.2.0.dist-info/WHEEL
genomehouse-1.2.0.dist-info/entry_points.txt
genomehouse-1.2.0.dist-info/top_level.txt
genomehouse-1.2.0.dist-info/RECORD
