Metadata-Version: 2.4
Name: genomehouse
Version: 1.2.0
Summary: Modular bioinformatics toolkit for sequence analysis, parsing, ML, and visualization.
Home-page: https://github.com/GenomeHouse/GenomeHouse-1.1
Author: Mubashir Ali
Author-email: GenomeHouse <mubashirali1837@gmail.com>
License: MIT License
Project-URL: Homepage, https://github.com/GenomeHouse/GenomeHouse-1.1
Project-URL: Documentation, https://github.com/GenomeHouse/GenomeHouse-1.1/tree/main/docs
Requires-Python: >=3.8
License-File: LICENSE
Requires-Dist: numpy
Requires-Dist: pandas
Requires-Dist: scikit-learn
Requires-Dist: matplotlib
Requires-Dist: seaborn
Requires-Dist: joblib
Dynamic: author
Dynamic: home-page
Dynamic: license-file
Dynamic: requires-python
